README
setup.py
kssh/__init__.py
kssh/kssh.py
kssh.egg-info/PKG-INFO
kssh.egg-info/SOURCES.txt
kssh.egg-info/dependency_links.txt
kssh.egg-info/entry_points.txt
kssh.egg-info/top_level.txt