Metadata-Version: 1.1
Name: kssh
Version: 1.2.0
Summary: kSSH is a simple utility for managing SSH hosts and tracking aliases in an SSH config file.
Home-page: https://github.com/kris-nova/kssh
Author: Kris Nova
Author-email: kris@nivenly.com
License: MIT
Keywords: SSH,ssh,manager,management,wrapper,config,configuration,tool,utility,cli,command line,command,line
Platform: UNKNOWN
Classifier: Development Status :: 5 - Production/Stable
Classifier: Intended Audience :: Developers
Classifier: Topic :: Software Development
Classifier: License :: OSI Approved :: MIT License
Classifier: Environment :: MacOS X
Classifier: Programming Language :: Python :: 2
Classifier: Programming Language :: Python :: 2.6
Classifier: Programming Language :: Python :: 2.7
